{
  "answer": {
    "displayWeekday": "Saturday",
    "displayDate": "April 11, 2026",
    "printDate": "2026-04-11",
    "centerLetter": "l",
    "outerLetters": [
      "d",
      "e",
      "g",
      "h",
      "i",
      "t"
    ],
    "validLetters": [
      "l",
      "d",
      "e",
      "g",
      "h",
      "i",
      "t"
    ],
    "pangrams": [
      "delight",
      "delighted",
      "highlighted",
      "lighted"
    ],
    "answers": [
      "delight",
      "delighted",
      "highlighted",
      "lighted",
      "delete",
      "deleted",
      "deli",
      "dell",
      "delt",
      "diddle",
      "diddled",
      "dill",
      "elide",
      "elided",
      "elite",
      "geld",
      "gelded",
      "gelee",
      "gelid",
      "gelled",
      "gelt",
      "giggle",
      "giggled",
      "gild",
      "gilded",
      "gill",
      "gilled",
      "gilt",
      "glee",
      "glide",
      "glided",
      "heel",
      "heeled",
      "held",
      "hell",
      "highlight",
      "hill",
      "hilled",
      "hilt",
      "idle",
      "idled",
      "lede",
      "ledge",
      "legged",
      "legit",
      "lidded",
      "lied",
      "liege",
      "light",
      "lilt",
      "lilted",
      "lite",
      "lithe",
      "little",
      "tell",
      "tilde",
      "tile",
      "tiled",
      "till",
      "tilled",
      "tilt",
      "tilted",
      "tilth",
      "title",
      "titled",
      "tittle"
    ],
    "id": 11995,
    "freeExpiration": 0,
    "editor": "Sam Ezersky"
  }
}