{
  "answer": {
    "displayWeekday": "Saturday",
    "displayDate": "June 6, 2026",
    "printDate": "2026-06-06",
    "centerLetter": "o",
    "outerLetters": [
      "e",
      "i",
      "l",
      "n",
      "t",
      "w"
    ],
    "validLetters": [
      "o",
      "e",
      "i",
      "l",
      "n",
      "t",
      "w"
    ],
    "pangrams": [
      "towline"
    ],
    "answers": [
      "towline",
      "intention",
      "into",
      "intone",
      "lento",
      "leonine",
      "lion",
      "loin",
      "loll",
      "lone",
      "loon",
      "loonie",
      "loot",
      "lotion",
      "lotto",
      "neon",
      "newton",
      "noel",
      "none",
      "nonet",
      "nonillion",
      "noon",
      "note",
      "notion",
      "oleo",
      "olio",
      "ollie",
      "onion",
      "online",
      "onto",
      "owlet",
      "tenon",
      "toil",
      "toile",
      "toilet",
      "toilette",
      "toll",
      "tone",
      "tonne",
      "tool",
      "toon",
      "toonie",
      "toot",
      "tootle",
      "tote",
      "towel",
      "towelette",
      "town",
      "townie",
      "willow",
      "winnow",
      "wino",
      "wont",
      "wonton",
      "wool",
      "woolen",
      "woot"
    ],
    "id": 23159,
    "freeExpiration": 0,
    "editor": "Sam Ezersky"
  }
}